LICENSE
MANIFEST.in
README.md
hgautohooks.py
setup.py
hg_autohooks.egg-info/PKG-INFO
hg_autohooks.egg-info/SOURCES.txt
hg_autohooks.egg-info/dependency_links.txt
hg_autohooks.egg-info/top_level.txt