Metadata-Version: 1.1
Name: hg-autohooks
Version: 0.1.0
Summary: Mercurial Autohooks Extension
Home-page: https://github.com/jribbens/hg-autohooks
Author: Jon Ribbens
Author-email: jon-hg-autohooks@unequivocal.co.uk
License: GPLv2+
Platform: UNKNOWN
Classifier: Development Status :: 4 - Beta
Classifier: Intended Audience :: Developers
Classifier: License :: OSI Approved :: GNU General Public License v2 or later (GPLv2+)
Classifier: Operating System :: OS Independent
Classifier: Programming Language :: Python
Classifier: Topic :: Software Development :: Version Control
